tests/__init__.py
tests/test_parser/__init__.py
tests/test_parser/test_album_parser.py
tests/test_parser/test_comment_parser.py
tests/test_parser/test_index_parser.py
tests/test_parser/test_info_parser.py
tests/test_parser/test_mblog_picAll_parser.py
tests/test_parser/test_page_parser.py
tests/test_parser/test_photo_parser.py
tests/test_parser/util.py
weibo_spider/__init__.py
weibo_spider/__main__.py
weibo_spider/config_sample.json
weibo_spider/config_util.py
weibo_spider/datetime_util.py
weibo_spider/logging.conf
weibo_spider/spider.py
weibo_spider/user.py
weibo_spider/weibo.py
weibo_spider/downloader/__init__.py
weibo_spider/downloader/avatar_picture_downloader.py
weibo_spider/downloader/downloader.py
weibo_spider/downloader/img_downloader.py
weibo_spider/downloader/origin_picture_downloader.py
weibo_spider/downloader/retweet_picture_downloader.py
weibo_spider/downloader/video_downloader.py
weibo_spider/parser/__init__.py
weibo_spider/parser/album_parser.py
weibo_spider/parser/comment_parser.py
weibo_spider/parser/index_parser.py
weibo_spider/parser/info_parser.py
weibo_spider/parser/mblog_picAll_parser.py
weibo_spider/parser/page_parser.py
weibo_spider/parser/parser.py
weibo_spider/parser/photo_parser.py
weibo_spider/parser/util.py
weibo_spider/writer/__init__.py
weibo_spider/writer/csv_writer.py
weibo_spider/writer/json_writer.py
weibo_spider/writer/kafka_writer.py
weibo_spider/writer/mongo_writer.py
weibo_spider/writer/mysql_writer.py
weibo_spider/writer/sqlite_writer.py
weibo_spider/writer/txt_writer.py
weibo_spider/writer/writer.py
weibo_spider-0.3.0.dist-info/METADATA
weibo_spider-0.3.0.dist-info/WHEEL
weibo_spider-0.3.0.dist-info/top_level.txt
weibo_spider-0.3.0.dist-info/RECORD
