Metadata-Version: 2.1
Name: weibo-spider
Version: 0.3.0
Summary: 新浪微博爬虫，用python爬取新浪微博数据。
Home-page: https://github.com/dataabc/weiboSpider
Author: Chen Lei
Author-email: chillychen1991@gmail.com
License: UNKNOWN
Platform: UNKNOWN
Classifier: Programming Language :: Python :: 3
Classifier: Operating System :: OS Independent
Requires-Python: >=3.6
Requires-Dist: absl-py
Requires-Dist: lxml
Requires-Dist: requests
Requires-Dist: tqdm
